sentry_mattermost_reformed/__init__.py
sentry_mattermost_reformed/client.py
sentry_mattermost_reformed/plugin.py
sentry_mattermost_reformed-0.0.3.dist-info/LICENSE
sentry_mattermost_reformed-0.0.3.dist-info/METADATA
sentry_mattermost_reformed-0.0.3.dist-info/WHEEL
sentry_mattermost_reformed-0.0.3.dist-info/entry_points.txt
sentry_mattermost_reformed-0.0.3.dist-info/top_level.txt
sentry_mattermost_reformed-0.0.3.dist-info/RECORD
