Metadata-Version: 2.1
Name: sentry-mattermost-reformed
Version: 0.0.3
Summary: A Sentry plugin to send Mattermost notifications.
Home-page: https://github.com/hadi2f244/sentry-mattermost-reformed
Author: Mohammad Hadi Azaddel
Author-email: m.h.azaddel@gmail.com
License: MIT
Keywords: sentry mattermost devops
Platform: UNKNOWN
Requires-Dist: requests
